ipgeocache/__init__.py
ipgeocache/__main__.py
ipgeocache/printers.py
ipgeocache/py.typed
ipgeocache-0.1.4.dist-info/LICENSE
ipgeocache-0.1.4.dist-info/METADATA
ipgeocache-0.1.4.dist-info/WHEEL
ipgeocache-0.1.4.dist-info/entry_points.txt
ipgeocache-0.1.4.dist-info/top_level.txt
ipgeocache-0.1.4.dist-info/RECORD
