Metadata-Version: 2.1
Name: ipgeocache
Version: 0.1.4
Summary: A small cache layer for IP geolocation info
Home-page: https://github.com/seanbreckenridge/ipgeocache
Author: Sean Breckenridge
Author-email: seanbrecke@gmail.com
License: MIT
Keywords: ip cache geolocate
Platform: UNKNOWN
Classifier: License :: OSI Approved :: MIT License
Classifier: Programming Language :: Python
Classifier: Programming Language :: Python :: 3
Classifier: Programming Language :: Python :: 3.6
Classifier: Programming Language :: Python :: 3.7
Classifier: Programming Language :: Python :: 3.8
Requires-Dist: requests
Requires-Dist: click
